ssm_diff-0.5.data/scripts/ssm-diff
ssm_diff-0.5.dist-info/METADATA
ssm_diff-0.5.dist-info/RECORD
ssm_diff-0.5.dist-info/WHEEL
ssm_diff-0.5.dist-info/top_level.txt
states/__init__.py
states/helpers.py
states/states.py
