Metadata-Version: 2.1
Name: ssm-diff
Version: 0.5
Summary: A tool to manage contents of AWS SSM Parameter Store
Home-page: https://github.com/runtheops/ssm-diff
Author: Sergey Motovilovets
Author-email: motovilovets.sergey@gmail.com
License: MIT
Download-URL: https://github.com/runtheops/ssm-diff/archive/0.5.tar.gz
Keywords: aws,ssm,parameter-store
Platform: UNKNOWN
Requires-Dist: termcolor
Requires-Dist: boto3
Requires-Dist: dpath
Requires-Dist: PyYAML
